jklm/__init__.py
jklm/exceptions.py
jklm/jklm.py
jklm_client-1.0.3.dist-info/LICENSE
jklm_client-1.0.3.dist-info/METADATA
jklm_client-1.0.3.dist-info/WHEEL
jklm_client-1.0.3.dist-info/top_level.txt
jklm_client-1.0.3.dist-info/RECORD
