Metadata-Version: 2.2
Name: jklm-client
Version: 1.0.3
Summary: Python client for the party game JKLM.fun
Author-email: Joseph Gerald <contact@jooo.tech>
Maintainer-email: Joseph Gerald <contact@jooo.tech>
License:                     GNU AFFERO GENERAL PUBLIC LICENSE
Project-URL: Homepage, https://github.com/joseph-gerald/jklm-py-client
Project-URL: Bug Reports, https://github.com/joseph-gerald/jklm-py-client/issues
Project-URL: Source, https://github.com/joseph-gerald/jklm-py-client
Keywords: JKLM.fun,game,client,python,async,websocket
Classifier: Development Status :: 3 - Alpha
Classifier: Intended Audience :: Developers
Classifier: Topic :: Internet :: WWW/HTTP :: Session
Classifier: Programming Language :: Python :: 3.7
Classifier: Programming Language :: Python :: 3.8
Classifier: Programming Language :: Python :: 3.9
Classifier: Programming Language :: Python :: 3.10
Classifier: Programming Language :: Python :: 3.11
Requires-Python: >=3.9
License-File: LICENSE
Requires-Dist: requests
Requires-Dist: websocket_client
